unitrade/__init__.c
unitrade/__init__.cpython-312-x86_64-linux-gnu.so
unitrade/init.c
unitrade/init.cpython-312-x86_64-linux-gnu.so
unitrade/unitrade.c
unitrade/unitrade.cpython-312-x86_64-linux-gnu.so
unitrade/account/__init__.c
unitrade/account/__init__.cpython-312-x86_64-linux-gnu.so
unitrade/account/daccount.c
unitrade/account/daccount.cpython-312-x86_64-linux-gnu.so
unitrade/account/ddata.c
unitrade/account/ddata.cpython-312-x86_64-linux-gnu.so
unitrade/account/faccount.c
unitrade/account/faccount.cpython-312-x86_64-linux-gnu.so
unitrade/account/fdata.c
unitrade/account/fdata.cpython-312-x86_64-linux-gnu.so
unitrade/cgcrypt/__init__.c
unitrade/cgcrypt/__init__.cpython-312-x86_64-linux-gnu.so
unitrade/cgcrypt/cgcrypt.c
unitrade/cgcrypt/cgcrypt.cpython-312-x86_64-linux-gnu.so
unitrade/cgcrypt/cgcryptcore.c
unitrade/cgcrypt/cgcryptcore.cpython-312-x86_64-linux-gnu.so
unitrade/cgcrypt/error_code.c
unitrade/cgcrypt/error_code.cpython-312-x86_64-linux-gnu.so
unitrade/cgcrypt/flag.c
unitrade/cgcrypt/flag.cpython-312-x86_64-linux-gnu.so
unitrade/core/__init__.c
unitrade/core/__init__.cpython-312-x86_64-linux-gnu.so
unitrade/core/common.c
unitrade/core/common.cpython-312-x86_64-linux-gnu.so
unitrade/core/error.c
unitrade/core/error.cpython-312-x86_64-linux-gnu.so
unitrade/core/httpclient.c
unitrade/core/httpclient.cpython-312-x86_64-linux-gnu.so
unitrade/core/limiter.c
unitrade/core/limiter.cpython-312-x86_64-linux-gnu.so
unitrade/core/logger.c
unitrade/core/logger.cpython-312-x86_64-linux-gnu.so
unitrade/core/sign.c
unitrade/core/sign.cpython-312-x86_64-linux-gnu.so
unitrade/core/tcpclient.c
unitrade/core/tcpclient.cpython-312-x86_64-linux-gnu.so
unitrade/core/tcpspec.c
unitrade/core/tcpspec.cpython-312-x86_64-linux-gnu.so
unitrade/product/__init__.c
unitrade/product/__init__.cpython-312-x86_64-linux-gnu.so
unitrade/product/domesticcontract.c
unitrade/product/domesticcontract.cpython-312-x86_64-linux-gnu.so
unitrade-1.0.0.5.dist-info/METADATA
unitrade-1.0.0.5.dist-info/WHEEL
unitrade-1.0.0.5.dist-info/top_level.txt
unitrade-1.0.0.5.dist-info/RECORD
